check_copyright/__init__.py
check_copyright/check_copyright.py
check_copyright/filter_files.py
check_copyright-0.2.2.dist-info/LICENSE
check_copyright-0.2.2.dist-info/METADATA
check_copyright-0.2.2.dist-info/WHEEL
check_copyright-0.2.2.dist-info/entry_points.txt
check_copyright-0.2.2.dist-info/top_level.txt
check_copyright-0.2.2.dist-info/RECORD
