Metadata-Version: 2.1
Name: check-copyright
Version: 0.2.2
Summary: Check copyright headers in a repository
Home-page: https://gitlab.com/ptr-project/check-copyright
Author: Kai Hoewelmeyer
License: MIT
Keywords: copyright
Platform: UNKNOWN
Requires-Python: >=3.6
